sekaibot/py.typed
sekaibot/plugins/__init__.py
sekaibot/plugins/apscheduler/__init__.py
sekaibot/plugins/apscheduler/config.py
sekaibot_plugin_apscheduler-0.1.3.dist-info/METADATA
sekaibot_plugin_apscheduler-0.1.3.dist-info/WHEEL
sekaibot_plugin_apscheduler-0.1.3.dist-info/RECORD
