Metadata-Version: 2.4
Name: sekaibot-plugin-apscheduler
Version: 0.1.3
Summary: APScheduler plugin for SekaiBot.
Project-URL: Repository, https://github.com/sekaibot-dev/sekaibot
Author-email: Kotodama <2682064633@qq.com>
License: MIT
Keywords: apscheduler,bot,chatbot,scheduling
Classifier: Development Status :: 3 - Alpha
Classifier: Framework :: AsyncIO
Classifier: Framework :: Robot Framework
Classifier: Framework :: Robot Framework :: Library
Classifier: License :: OSI Approved :: MIT License
Classifier: Operating System :: OS Independent
Classifier: Programming Language :: Python :: 3
Classifier: Topic :: Communications :: Chat
Requires-Python: >=3.9
Requires-Dist: apscheduler<4.0,>=3.7
Requires-Dist: sekaibot==0.1.3
